[
  {
    "Datum und Zeit": "2023-04-11, 07:00",
    "Stärke der Limitation": 6,
    "Symptome und Schweregrade": {
      "Taubheitsgefühl in den Beinen": 7,
      "Kribbeln in den Beinen": 4
    },
    "Medikament und Dosierung": "-",
    "Kommentare": "-"
  },
  {
    "Datum und Zeit": "2023-04-11, 11:00",
    "Stärke der Limitation": 6,
    "Symptome und Schweregrade": {
      "Taubheitsgefühl in den Beinen": 6,
      "Kribbeln in den Beinen": 4
    },
    "Medikament und Dosierung": "-",
    "Kommentare": "-"
  },
  {
    "Datum und Zeit": "2023-04-11, 15:00",
    "Stärke der Limitation": 8,
    "Symptome und Schweregrade": {
      "Kribbeln in den Beinen": 7,
      "Steifheit der Muskeln": 6
    },
    "Medikament und Dosierung": "-",
    "Kommentare": "-"
  },
  {
    "Datum und Zeit": "2023-04-11, 19:00",
    "Stärke der Limitation": 9,
    "Symptome und Schweregrade": {
      "Lähmungserscheinungen": 8
    },
    "Medikament und Dosierung": "-",
    "Kommentare": "-"
  },
  {
    "Datum und Zeit": "2023-04-11, 23:00",
    "Stärke der Limitation": 6,
    "Symptome und Schweregrade": {
      "Taubheitsgefühl in den Armen": 6,
      "Taubheitsgefühl in den Beinen": 7,
      "Steifheit der Muskeln": 5
    },
    "Medikament und Dosierung": "-",
    "Kommentare": "-"
  },
  {
    "Datum und Zeit": "2023-04-12, 06:45",
    "Stärke der Limitation": 5,
    "Symptome und Schweregrade": {
      "Rasche Erschöpfung": 5,
      "Tremor (Zittern)": 6
    },
    "Medikament und Dosierung": "-",
    "Kommentare": "-"
  },
  {
    "Datum und Zeit": "2023-04-12, 11:00",
    "Stärke der Limitation": 5,
    "Symptome und Schweregrade": {
      "Rasche Erschöpfung": 5,
      "Tremor (Zittern)": 5
    },
    "Medikament und Dosierung": "-",
    "Kommentare": "-"
  },
  {
    "Datum und Zeit": "2023-04-12, 15:00",
    "Stärke der Limitation": 4,
    "Symptome und Schweregrade": {
      "Tremor (Zittern)": 5,
      "Steifheit der Muskeln": 4
    },
    "Medikament und Dosierung": "-",
    "Kommentare": "-"
  },
  {
    "Datum und Zeit": "2023-04-12, 19:00",
    "Stärke der Limitation": 6,
    "Symptome und Schweregrade": {
      "Tremor (Zittern)": 7,
      "Steifheit der Muskeln": 5
    },
    "Medikament und Dosierung": "-",
    "Kommentare": "-"
  },
  {
    "Datum und Zeit": "2023-04-12, 23:00",
    "Stärke der Limitation": 3,
    "Symptome und Schweregrade": {
      "Steifheit der Muskeln": 3,
      "Rasche Erschöpfung": 4
    },
    "Medikament und Dosierung": "-",
    "Kommentare": "-"
  },
  {
    "Datum und Zeit": "2023-04-13, 07:15",
    "Stärke der Limitation": 5,
    "Symptome und Schweregrade": {
      "Rasche Erschöpfung": 6,
      "Gleichgewichtsstörungen": 5
    },
    "Medikament und Dosierung": "-",
    "Kommentare": "schlecht geschlafen"
  },
  {
    "Datum und Zeit": "2023-04-13, 11:00",
    "Stärke der Limitation": 7,
    "Symptome und Schweregrade": {
      "Taubheitsgefühl in den Armen": 7,
      "Kribbeln in den Armen": 6
    },
    "Medikament und Dosierung": "",
    "Kommentare": ""
  }
]